radiantai/__init__.py
radiantai/instrumentor.py
radiantai-0.137.0.dist-info/METADATA
radiantai-0.137.0.dist-info/WHEEL
radiantai-0.137.0.dist-info/RECORD
