Metadata-Version: 2.1
Name: radiantai
Version: 0.137.0
Summary: Radiant SDK
License: MIT
Author: nkulkarni
Author-email: nitish.kulkarni@gmail.com
Requires-Python: >=3.12,<3.13
Classifier: License :: OSI Approved :: MIT License
Classifier: Programming Language :: Python :: 3
Requires-Dist: openai (>=1.40.3,<2.0.0)
Requires-Dist: openinference-instrumentation-openai (>=0.1.12,<0.2.0)
Requires-Dist: opentelemetry-api (>=1.26.0,<2.0.0)
Requires-Dist: opentelemetry-exporter-otlp-proto-http (>=1.26.0,<2.0.0)
Requires-Dist: opentelemetry-sdk (>=1.26.0,<2.0.0)
Requires-Dist: requests (>=2.32.3,<3.0.0)
